{
  "resourceType": "ValueSet",
  "id": "33014",
  "meta": {
    "lastUpdated": "2022-03-02T19:38:45.811-05:00"
  },
  "url": "https://www.ncqa.org/fhir/valueset/2.16.840.1.113883.3.464.1004.1509",
  "identifier": [
    {
      "value": "2.16.840.1.113883.3.464.1004.1509"
    }
  ],
  "version": "2022-03-31",
  "name": "37_Weeks_Gestation",
  "title": "37 Weeks Gestation",
  "status": "active",
  "expansion": {
    "timestamp": "2022-03-24T18:47:13-04:00",
    "total": 2,
    "offset": 0,
    "contains": [
      {
        "system": "http://snomed.info/sct",
        "version": "2021.09.21AA",
        "code": "43697006",
        "display": "Gestation period, 37 weeks"
      },
      {
        "system": "http://hl7.org/fhir/sid/icd-10-cm",
        "version": "2022.1.21AA",
        "code": "Z3A.37",
        "display": "37 weeks gestation of pregnancy"
      }
    ]
  }
}